{
  "config": "configs/bitnet_32x512.yaml",
  "versions": {
    "python": "3.12.3",
    "torch": "2.11.0+cu128",
    "cuda": "12.8",
    "triton": "3.6.0",
    "gpu": "NVIDIA GeForce RTX 5070 Ti Laptop GPU"
  },
  "results": [
    {
      "mode": "fp_chainrule",
      "initial_ce": 5.639921188354492,
      "final_ce": 1.438407301902771,
      "ce_delta": 4.201513886451721,
      "tokens_sec": 1665.6981477799068,
      "ms_step": 76.84465530000277,
      "peak_cuda_memory_gb": 2.078098944,
      "params": 101171968,
      "ternary": "n/a",
      "gamma_mean": "n/a",
      "backend": "fp",
      "native_kernel": false,
      "packed_1p58bit": false,
      "completed": true
    },
    {
      "mode": "fp_mono_update_every_2",
      "initial_ce": 5.639921188354492,
      "final_ce": 1.937263011932373,
      "ce_delta": 3.702658176422119,
      "tokens_sec": 3203.46129989078,
      "ms_step": 39.95678050000606,
      "peak_cuda_memory_gb": 2.080196096,
      "params": 101171968,
      "ternary": "n/a",
      "gamma_mean": "n/a",
      "backend": "fp",
      "native_kernel": false,
      "packed_1p58bit": false,
      "completed": true
    },
    {
      "mode": "bitnet_fake_chainrule",
      "initial_ce": 5.519841194152832,
      "final_ce": 1.3947275876998901,
      "ce_delta": 4.125113606452942,
      "tokens_sec": 1522.4173178781386,
      "ms_step": 84.07681553333835,
      "peak_cuda_memory_gb": 2.290139136,
      "params": 101171968,
      "ternary": "37.5/25.1/37.4",
      "gamma_mean": 0.01942276817479337,
      "backend": "fake",
      "native_kernel": false,
      "packed_1p58bit": false,
      "completed": true
    },
    {
      "mode": "bitnet_fake_mono_update_every_2",
      "initial_ce": 5.519841194152832,
      "final_ce": 1.544647216796875,
      "ce_delta": 3.975193977355957,
      "tokens_sec": 2314.7026601260723,
      "ms_step": 55.298679266661566,
      "peak_cuda_memory_gb": 2.878951424,
      "params": 101171968,
      "ternary": "37.5/25.1/37.4",
      "gamma_mean": 0.01939417127259942,
      "backend": "fake",
      "native_kernel": false,
      "packed_1p58bit": false,
      "completed": true
    },
    {
      "mode": "bitnet_native_chainrule",
      "initial_ce": 5.519804954528809,
      "final_ce": 1.3951067924499512,
      "ce_delta": 4.124698162078857,
      "tokens_sec": 1359.8253030451763,
      "ms_step": 94.12973836665515,
      "peak_cuda_memory_gb": 2.080196096,
      "params": 101171968,
      "ternary": "37.5/25.1/37.4",
      "gamma_mean": 0.019422810286456763,
      "backend": "native",
      "native_kernel": true,
      "packed_1p58bit": false,
      "completed": true
    },
    {
      "mode": "bitnet_native_mono_update_every_2",
      "initial_ce": 5.519804954528809,
      "final_ce": 1.5449352264404297,
      "ce_delta": 3.974869728088379,
      "tokens_sec": 1860.4449055737052,
      "ms_step": 68.80074740000357,
      "peak_cuda_memory_gb": 2.180337664,
      "params": 101171968,
      "ternary": "37.5/25.1/37.4",
      "gamma_mean": 0.019394193097313706,
      "backend": "native",
      "native_kernel": true,
      "packed_1p58bit": false,
      "completed": true
    }
  ]
}